openapi_pydantic/__init__.py
openapi_pydantic/compat.py
openapi_pydantic/py.typed
openapi_pydantic/util.py
openapi_pydantic/v3/__init__.py
openapi_pydantic/v3/parser.py
openapi_pydantic/v3/v3_0/README.md
openapi_pydantic/v3/v3_0/__init__.py
openapi_pydantic/v3/v3_0/callback.py
openapi_pydantic/v3/v3_0/components.py
openapi_pydantic/v3/v3_0/contact.py
openapi_pydantic/v3/v3_0/datatype.py
openapi_pydantic/v3/v3_0/discriminator.py
openapi_pydantic/v3/v3_0/encoding.py
openapi_pydantic/v3/v3_0/example.py
openapi_pydantic/v3/v3_0/external_documentation.py
openapi_pydantic/v3/v3_0/header.py
openapi_pydantic/v3/v3_0/info.py
openapi_pydantic/v3/v3_0/license.py
openapi_pydantic/v3/v3_0/link.py
openapi_pydantic/v3/v3_0/media_type.py
openapi_pydantic/v3/v3_0/oauth_flow.py
openapi_pydantic/v3/v3_0/oauth_flows.py
openapi_pydantic/v3/v3_0/open_api.py
openapi_pydantic/v3/v3_0/operation.py
openapi_pydantic/v3/v3_0/parameter.py
openapi_pydantic/v3/v3_0/path_item.py
openapi_pydantic/v3/v3_0/paths.py
openapi_pydantic/v3/v3_0/reference.py
openapi_pydantic/v3/v3_0/request_body.py
openapi_pydantic/v3/v3_0/response.py
openapi_pydantic/v3/v3_0/responses.py
openapi_pydantic/v3/v3_0/schema.py
openapi_pydantic/v3/v3_0/security_requirement.py
openapi_pydantic/v3/v3_0/security_scheme.py
openapi_pydantic/v3/v3_0/server.py
openapi_pydantic/v3/v3_0/server_variable.py
openapi_pydantic/v3/v3_0/tag.py
openapi_pydantic/v3/v3_0/util.py
openapi_pydantic/v3/v3_0/xml.py
openapi_pydantic/v3/v3_1/README.md
openapi_pydantic/v3/v3_1/__init__.py
openapi_pydantic/v3/v3_1/callback.py
openapi_pydantic/v3/v3_1/components.py
openapi_pydantic/v3/v3_1/contact.py
openapi_pydantic/v3/v3_1/datatype.py
openapi_pydantic/v3/v3_1/discriminator.py
openapi_pydantic/v3/v3_1/encoding.py
openapi_pydantic/v3/v3_1/example.py
openapi_pydantic/v3/v3_1/external_documentation.py
openapi_pydantic/v3/v3_1/header.py
openapi_pydantic/v3/v3_1/info.py
openapi_pydantic/v3/v3_1/license.py
openapi_pydantic/v3/v3_1/link.py
openapi_pydantic-0.5.0.dist-info/LICENSE
openapi_pydantic-0.5.0.dist-info/METADATA
openapi_pydantic-0.5.0.dist-info/WHEEL
openapi_pydantic-0.5.0.dist-info/RECORD
