Metadata-Version: 2.1
Name: openapi-pydantic
Version: 0.5.0
Summary: Pydantic OpenAPI schema implementation
Home-page: https://github.com/mike-oakley/openapi-pydantic
License: MIT
Keywords: openapi,schema,parser,pydantic,validation
Author: Mike Oakley
Author-email: mike-oakley@users.noreply.github.com
Requires-Python: >=3.8,<4.0
Classifier: Framework :: Pydantic
Classifier: License :: OSI Approved :: MIT License
Classifier: Operating System :: OS Independent
Classifier: Programming Language :: Python :: 3
Classifier: Programming Language :: Python :: 3.8
Classifier: Programming Language :: Python :: 3.9
Classifier: Programming Language :: Python :: 3.10
Classifier: Programming Language :: Python :: 3.11
Classifier: Programming Language :: Python :: 3.12
Requires-Dist: pydantic (>=1.8)
Project-URL: Repository, https://github.com/mike-oakley/openapi-pydantic
Project-URL: changelog, https://github.com/mike-oakley/openapi-pydantic/releases
